bilibili_downloader/__init__.py
bilibili_downloader/downloader.py
bilibili_downloader/exceptions.py
bilibili_downloader/models.py
bilibili_downloader/utils.py
bilibili_downloader-1.0.0.dist-info/licenses/LICENSE
bilibili_downloader-1.0.0.dist-info/METADATA
bilibili_downloader-1.0.0.dist-info/WHEEL
bilibili_downloader-1.0.0.dist-info/top_level.txt
bilibili_downloader-1.0.0.dist-info/RECORD
