Metadata-Version: 2.4
Name: bilibili-downloader
Version: 1.0.0
Summary: 一个简单易用的B站视频下载Python库
Home-page: https://github.com/twwch/bilibili-downloader
Author: Your Name
Author-email: Your Name <your.email@example.com>
License: MIT
Project-URL: Homepage, https://github.com/twwch/bilibili-downloader
Project-URL: Documentation, https://github.com/twwch/bilibili-downloader#readme
Project-URL: Repository, https://github.com/twwch/bilibili-downloader.git
Project-URL: Bug Tracker, https://github.com/twwch/bilibili-downloader/issues
Keywords: bilibili,video,download,audio,api
Classifier: Development Status :: 4 - Beta
Classifier: Intended Audience :: Developers
Classifier: License :: OSI Approved :: MIT License
Classifier: Programming Language :: Python :: 3
Classifier: Programming Language :: Python :: 3.7
Classifier: Programming Language :: Python :: 3.8
Classifier: Programming Language :: Python :: 3.9
Classifier: Programming Language :: Python :: 3.10
Classifier: Programming Language :: Python :: 3.11
Classifier: Operating System :: OS Independent
Classifier: Topic :: Multimedia :: Video
Classifier: Topic :: Software Development :: Libraries :: Python Modules
Requires-Python: >=3.7
License-File: LICENSE
Requires-Dist: aiohttp>=3.8.0
Requires-Dist: httpx>=0.24.0
Requires-Dist: requests>=2.25.0
Requires-Dist: ffmpy3>=0.2.4
Provides-Extra: dev
Requires-Dist: pytest>=7.0.0; extra == "dev"
Requires-Dist: pytest-asyncio>=0.18.0; extra == "dev"
Requires-Dist: black>=22.0.0; extra == "dev"
Requires-Dist: flake8>=4.0.0; extra == "dev"
Requires-Dist: twine>=4.0.0; extra == "dev"
Requires-Dist: wheel>=0.38.0; extra == "dev"
Dynamic: author
Dynamic: home-page
Dynamic: license-file
Dynamic: requires-python
